kostal_ardexa.py
kostal_ardexa-0.2.1.dist-info/DESCRIPTION.rst
kostal_ardexa-0.2.1.dist-info/METADATA
kostal_ardexa-0.2.1.dist-info/RECORD
kostal_ardexa-0.2.1.dist-info/WHEEL
kostal_ardexa-0.2.1.dist-info/entry_points.txt
kostal_ardexa-0.2.1.dist-info/metadata.json
kostal_ardexa-0.2.1.dist-info/top_level.txt
